LICENSE
README.md
setup.py
py_myb.egg-info/PKG-INFO
py_myb.egg-info/SOURCES.txt
py_myb.egg-info/dependency_links.txt
py_myb.egg-info/not-zip-safe
py_myb.egg-info/requires.txt
py_myb.egg-info/top_level.txt
py_mybatis/__init__.py
py_mybatis/funs.py
py_mybatis/logger.py
py_mybatis/mapper.py
py_mybatis/mapper_func.py
py_mybatis/py_mybatis_ex.py
py_mybatis/sql_params.py
py_mybatis/sql_util.py
py_mybatis/string_util.py
py_mybatis/type_handler.py
py_mybatis/sql/__init__.py
py_mybatis/sql/mybatis_sql_session.py
py_mybatis/sql/pdbc_sql_template.py