Metadata-Version: 2.1
Name: py-myb
Version: 0.1.0
Summary: python mybatis
Home-page: https://github.com/dushitaoyuan/py_mybatis.git
Author: dushitaoyuan
Author-email: dushitaoyuan@gmail.com
License: Apache 2.0
Keywords: mybatis py_mybatis dynamic sql orm
Platform: UNKNOWN
Classifier: Development Status :: 3 - Alpha
Classifier: Intended Audience :: Developers
Classifier: License :: OSI Approved :: Apache Software License
Classifier: Operating System :: OS Independent
Classifier: Programming Language :: Python :: 3
Classifier: Programming Language :: Python :: 3.4
Classifier: Programming Language :: Python :: 3.5
Classifier: Programming Language :: Python :: 3.6
Classifier: Programming Language :: Python :: 3.7
License-File: LICENSE
